{
  "all": {
    "parent": "bibliocraft:block/template/table/all",
    "textures": {
      "texture": "silentgear:block/netherwood_planks"
    }
  },
  "curve": {
    "parent": "bibliocraft:block/template/table/curve",
    "textures": {
      "texture": "silentgear:block/netherwood_planks"
    }
  },
  "loader": "bibliocraft:table",
  "none": {
    "parent": "bibliocraft:block/template/table/none",
    "textures": {
      "texture": "silentgear:block/netherwood_planks"
    }
  },
  "one": {
    "parent": "bibliocraft:block/template/table/one",
    "textures": {
      "texture": "silentgear:block/netherwood_planks"
    }
  },
  "straight": {
    "parent": "bibliocraft:block/template/table/straight",
    "textures": {
      "texture": "silentgear:block/netherwood_planks"
    }
  },
  "textures": {
    "particle": "silentgear:block/netherwood_planks"
  },
  "three": {
    "parent": "bibliocraft:block/template/table/three",
    "textures": {
      "texture": "silentgear:block/netherwood_planks"
    }
  }
}