{
  "neoforge:conditions": [
    {
      "type": "neoforge:mod_loaded",
      "modid": "occultism"
    }
  ],
  "type": "minecraft:crafting_shaped",
  "category": "misc",
  "group": "bibliocraft:flat_seat_backs",
  "key": {
    "R": {
      "tag": "c:rods/wooden"
    },
    "S": {
      "item": "occultism:otherplanks_slab"
    },
    "W": {
      "item": "minecraft:blue_wool"
    }
  },
  "pattern": [
    "RWR",
    "RSR",
    "R R"
  ],
  "result": {
    "count": 1,
    "id": "bibliocraft:blue_occultism_otherplanks_flat_seat_back"
  }
}