{
  "neoforge:conditions": [
    {
      "type": "neoforge:mod_loaded",
      "modid": "biomeswevegone"
    }
  ],
  "type": "minecraft:crafting_shaped",
  "category": "misc",
  "group": "bibliocraft:tall_seat_backs",
  "key": {
    "#": {
      "item": "bibliocraft:black_biomeswevegone_palm_flat_seat_back"
    },
    "S": {
      "item": "biomeswevegone:palm_slab"
    }
  },
  "pattern": [
    "S",
    "#"
  ],
  "result": {
    "count": 1,
    "id": "bibliocraft:black_biomeswevegone_palm_tall_seat_back"
  }
}