{
  "neoforge:conditions": [
    {
      "type": "neoforge:mod_loaded",
      "modid": "wwizardry"
    }
  ],
  "type": "minecraft:crafting_shaped",
  "category": "misc",
  "group": "bibliocraft:potion_shelves",
  "key": {
    "#": {
      "item": "minecraft:glass_bottle"
    },
    "P": {
      "item": "wwizardry:mycha_planks"
    },
    "S": {
      "item": "wwizardry:mycha_slab"
    }
  },
  "pattern": [
    "SSS",
    "P#P",
    "SSS"
  ],
  "result": {
    "count": 1,
    "id": "bibliocraft:wwizardry_mycha_potion_shelf"
  }
}